power_switch_pro/__init__.py
power_switch_pro/auth.py
power_switch_pro/autoping.py
power_switch_pro/client.py
power_switch_pro/config.py
power_switch_pro/exceptions.py
power_switch_pro/meters.py
power_switch_pro/outlets.py
power_switch_pro/script.py
power_switch_pro-1.1.1.dist-info/licenses/LICENSE
power_switch_pro-1.1.1.dist-info/METADATA
power_switch_pro-1.1.1.dist-info/WHEEL
power_switch_pro-1.1.1.dist-info/top_level.txt
power_switch_pro-1.1.1.dist-info/RECORD
