Metadata-Version: 2.4
Name: power_switch_pro
Version: 1.1.1
Summary: Python library for Digital Loggers Power Switch Pro REST API
Home-page: https://github.com/bryan/power_switch_pro
Author: Bryan Kemp
Author-email: Bryan Kemp <bryan@kempville.com>
License: BSD-3-Clause
Project-URL: Homepage, https://github.com/bryankemp/power_switch_pro
Project-URL: Documentation, https://power-switch-pro.readthedocs.io
Project-URL: Repository, https://github.com/bryankemp/power_switch_pro
Project-URL: Issues, https://github.com/bryankemp/power_switch_pro/issues
Keywords: power,switch,digital-loggers,automation,pdu
Classifier: Development Status :: 5 - Production/Stable
Classifier: Intended Audience :: Developers
Classifier: Topic :: Home Automation
Classifier: Topic :: System :: Hardware
Classifier: License :: OSI Approved :: BSD License
Classifier: Programming Language :: Python :: 3
Classifier: Programming Language :: Python :: 3.9
Classifier: Programming Language :: Python :: 3.10
Classifier: Programming Language :: Python :: 3.11
Classifier: Programming Language :: Python :: 3.12
Requires-Python: >=3.7
License-File: LICENSE
Requires-Dist: requests>=2.25.0
Provides-Extra: dev
Requires-Dist: pytest>=7.0.0; extra == "dev"
Requires-Dist: pytest-cov>=3.0.0; extra == "dev"
Requires-Dist: pytest-mock>=3.10.0; extra == "dev"
Requires-Dist: responses>=0.22.0; extra == "dev"
Requires-Dist: black>=22.0.0; extra == "dev"
Requires-Dist: ruff>=0.0.200; extra == "dev"
Requires-Dist: mypy>=0.990; extra == "dev"
Requires-Dist: types-requests>=2.28.0; extra == "dev"
Requires-Dist: pre-commit>=3.0.0; extra == "dev"
Requires-Dist: bandit[toml]>=1.7.0; extra == "dev"
Requires-Dist: safety>=2.0.0; extra == "dev"
Provides-Extra: docs
Requires-Dist: sphinx>=5.0.0; extra == "docs"
Requires-Dist: sphinx-rtd-theme>=1.0.0; extra == "docs"
Requires-Dist: sphinx-autodoc-typehints>=1.19.0; extra == "docs"
Dynamic: author
Dynamic: home-page
Dynamic: license-file
Dynamic: requires-python
